nonebot_plugin_pjsekaihelper/__init__.py
nonebot_plugin_pjsekaihelper/__main__.py
nonebot_plugin_pjsekaihelper/config.py
nonebot_plugin_pjsekaihelper/render.py
nonebot_plugin_pjsekaihelper/resource.py
nonebot_plugin_pjsekaihelper/utils.py
nonebot_plugin_pjsekaihelper-1.2.10.dist-info/LICENSE
nonebot_plugin_pjsekaihelper-1.2.10.dist-info/LICENSE-SekaiStickers
nonebot_plugin_pjsekaihelper-1.2.10.dist-info/METADATA
nonebot_plugin_pjsekaihelper-1.2.10.dist-info/WHEEL
nonebot_plugin_pjsekaihelper-1.2.10.dist-info/top_level.txt
nonebot_plugin_pjsekaihelper-1.2.10.dist-info/RECORD
