Metadata-Version: 2.1
Name: nonebot-plugin-pjsekaihelper
Version: 1.2.10
Summary: 世界计划插件，拥有组建车队、生成角色表情包、模拟抽卡等功能，持续开发中
Author: Ant1
Author-email: glz15757339816@gmail.com
Maintainer-email: Ant1 <glz15757339816@gmail.com>
License: MIT License
Project-URL: homepage, https://github.com/Ant1816/nonebot-plugin-pjsekaihelper
Project-URL: documentation, https://github.com/Ant1816/nonebot-plugin-pjsekaihelper/blob/master/README.md
Project-URL: repository, https://github.com/Ant1816/nonebot-plugin-pjsekaihelper
Project-URL: changelog, https://github.com/Ant1816/nonebot-plugin-pjsekaihelper/commits/master/
Keywords: nonebot2,projectsekai,pjsk
Classifier: License :: OSI Approved :: MIT License
Classifier: Development Status :: 5 - Production/Stable
Classifier: Programming Language :: Python :: 3.12
Requires-Python: >=3.9
License-File: LICENSE
License-File: LICENSE-SekaiStickers
Requires-Dist: nonebot2>=2.3.1
Requires-Dist: nonebot_plugin_localstore>=0.7.1
Requires-Dist: nonebot-adapter-onebot>=2.1.0
Requires-Dist: httpx>=0.27.0
Requires-Dist: anyio>=4.4.0
Requires-Dist: nonebot-plugin-alconna>=0.48.0
Requires-Dist: nonebot-plugin-htmlrender>=0.3.2
Requires-Dist: jinja2>=3.1.4
Requires-Dist: yarl>=1.9.4
Requires-Dist: pydantic>=2.0
Provides-Extra: test
